nonebot_plugin_envious/__init__.py
nonebot_plugin_envious/config.py
nonebot_plugin_envious/envious.py
nonebot_plugin_envious-0.1.5.dist-info/WHEEL
nonebot_plugin_envious-0.1.5.dist-info/METADATA
nonebot_plugin_envious-0.1.5.dist-info/RECORD
