Metadata-Version: 2.3
Name: nonebot-plugin-envious
Version: 0.1.5
Summary: 羡慕 koishi
Keywords: nonebot,nonebot2,envious,koishi,羡慕
Author: fllesser
Author-email: fllesser <fllessive@gmail.com>
Requires-Dist: nonebot2>=2.4.3,<3.0.0
Requires-Dist: nonebot-adapter-onebot>=2.4.6
Requires-Dist: nonebot-plugin-localstore>=0.7.4
Requires-Dist: nonebot-plugin-apscheduler>=0.5.0
Requires-Python: >=3.10
Project-URL: Changelog, https://github.com/fllesser/nonebot-plugin-envious/blob/main/CHANGELOG.md
Project-URL: Homepage, https://github.com/fllesser/nonebot-plugin-envious
Project-URL: Issues, https://github.com/fllesser/nonebot-plugin-envious/issues
Project-URL: Repository, https://github.com/fllesser/nonebot-plugin-envious.git
